Workbook

Sheet 📋 Отчёт P&L
A1: УЧЕБНЫЙ P&L — ООО «Языковая студия» · Январь–Март 2025
A2: 📌 P&L показывает движение «по начислению» — доход признаётся, когда услуга оказана (а не когда пришли деньги, как в ДДС). Поэтому цифры P&L и ДДС за один месяц обычно не совпадают.
A4: Показатель | B4: Январь | C4: Февраль | D4: Март | F4: ИТОГО за квартал | G4: % от выручки (за квартал)
A5: ▌ ВЫРУЧКА
A6: Групповые курсы | B6: 8000000 | C6: 8500000 | D6: 10200000 | F6: =SUM(B6:D6) -> 26700000 | G6: =F6/$F$9 -> 0.60681818
A7: Индивидуальные занятия | B7: 3200000 | C7: 3500000 | D7: 4100000 | F7: =SUM(B7:D7) -> 10800000 | G7: =F7/$F$9 -> 0.24545455
A8: B2B консультации | B8: 1500000 | C8: 2000000 | D8: 3000000 | F8: =SUM(B8:D8) -> 6500000 | G8: =F8/$F$9 -> 0.14772727
A9: ИТОГО ВЫРУЧКА | B9: =SUM(B6:B8) -> 12700000 | C9: =SUM(C6:C8) -> 14000000 | D9: =SUM(D6:D8) -> 17300000 | F9: =SUM(B9:D9) -> 44000000 | G9: 100.0%
A11: ▌ СЕБЕСТОИМОСТЬ (прямые затраты на услуги)
A12: Оплата приглашённым преподавателям (~35% выручки) | B12: 4445000 | C12: 4900000 | D12: 6055000 | F12: =SUM(B12:D12) -> 15400000 | G12: =F12/F9 -> 0.35
A15: ВАЛОВАЯ ПРИБЫЛЬ = Выручка − Себестоимость | B15: =B9-B12 -> 8255000 | C15: =C9-C12 -> 9100000 | D15: =D9-D12 -> 11245000 | F15: =F9-F12 -> 28600000 | G15: =F15/F9 -> 0.65
A16: Валовая маржа — сколько остаётся «на круг» после прямых затрat на продукт
A18: ▌ ОПЕРАЦИОННЫЕ РАСХОДЫ
A19: Оплата труда (штат) | B19: 2800000 | C19: 2800000 | D19: 2950000 | F19: =SUM(B19:D19) -> 8550000 | G19: =F19/$F$24 -> 0.45406267
A20: Аренда | B20: 1500000 | C20: 1500000 | D20: 1500000 | F20: =SUM(B20:D20) -> 4500000 | G20: =F20/$F$24 -> 0.23898035
A21: Маркетинг | B21: 800000 | C21: 1200000 | D21: 2100000 | F21: =SUM(B21:D21) -> 4100000 | G21: =F21/$F$24 -> 0.21773765
A22: Офисные расходы | B22: 350000 | C22: 320000 | D22: 410000 | F22: =SUM(B22:D22) -> 1080000 | G22: =F22/$F$24 -> 0.057355284
A23: Амортизация оборудования | B23: 200000 | C23: 200000 | D23: 200000 | F23: =SUM(B23:D23) -> 600000 | G23: =F23/$F$24 -> 0.031864047
A24: ИТОГО ОПЕРАЦИОННЫЕ РАСХОДЫ | B24: =SUM(B19:B23) -> 5650000 | C24: =SUM(C19:C23) -> 6020000 | D24: =SUM(D19:D23) -> 7160000 | F24: =SUM(B24:D24) -> 18830000 | G24: =F24/F9 -> 0.42795455
A26: ОПЕРАЦИОННАЯ ПРИБЫЛЬ = Валовая прибыль − Опер. расходы | B26: =B15-B24 -> 2605000 | C26: =C15-C24 -> 3080000 | D26: =D15-D24 -> 4085000 | F26: =F15-F24 -> 9770000 | G26: =F26/F9 -> 0.22204545
A27: Операционная маржа — зарабатывает ли бизнес на своей основной деятельности
A29: ▌ ПРОЧИЕ СТАТЬИ
A30: Проценты по кредиту | B30: 150000 | C30: 150000 | D30: 150000 | F30: =SUM(B30:D30) -> 450000
A31: Прибыль до налогообложения | B31: =B26-B30 -> 2455000 | C31: =C26-C30 -> 2930000 | D31: =D26-D30 -> 3935000 | F31: =F26-F30 -> 9320000
A32: Налог на прибыль (15%) | B32: =B31*0.15 -> 368250 | C32: =C31*0.15 -> 439500 | D32: =D31*0.15 -> 590250 | F32: =F31*0.15 -> 1398000
A34: ЧИСТАЯ ПРИБЫЛЬ (то, что реально осталось бизнесу) | B34: =B31-B32 -> 2086750 | C34: =C31-C32 -> 2490500 | D34: =D31-D32 -> 3344750 | F34: =F31-F32 -> 7922000 | G34: =F34/F9 -> 0.18004545
A35: Чистая маржа — итоговая «отдача» с каждой суммы заработанной выручки
A37: 🔑 КЛЮЧЕВАЯ ИДЕЯ: Каждый уровень прибыли отвечает на свой вопрос — валовая показывает здоровье продукта, операционная — здоровье основной деятельности, чистая — итог с учётом всего. Выручка растёт каждый месяц (+36% за квартал), и при этом чистая маржа тоже растёт (16,4% → 19,3%) — это здоровый рост, в отличие от Кейса 2.

Sheet 📈 Дашборд
A1: ДАШБОРД P&L — ООО «Языковая студия» · Январь–Март 2025
A2: ВЫРУЧКА ЗА КВАРТАЛ | F2: ВАЛОВАЯ МАРЖА | K2: ОПЕРАЦИОННАЯ МАРЖА | P2: ЧИСТАЯ МАРЖА (СРЕДН.)
A3: ='📋 Отчёт P&L'!F9 -> 44000000 | F3: ='📋 Отчёт P&L'!G15 -> 0.65 | K3: ='📋 Отчёт P&L'!G26 -> 0.22204545 | P3: ='📋 Отчёт P&L'!G34 -> 0.18004545
A6: Месяц | B6: Выручка | C6: Расходы (с/с + опер.) | D6: Чистая прибыль | F6: Уровень | G6: Сумма за квартал | I6: Статья | J6: Сумма | L6: Месяц | M6: Валовая маржа | N6: Операционная маржа | O6: Чистая маржа
A7: Январь | B7: ='📋 Отчёт P&L'!B9 -> 12700000 | C7: ='📋 Отчёт P&L'!B12+'📋 Отчёт P&L'!B24 -> 10095000 | D7: ='📋 Отчёт P&L'!B34 -> 2086750 | F7: Выручка | G7: ='📋 Отчёт P&L'!F9 -> 44000000 | I7: Себестоимость (преподаватели) | J7: ='📋 Отчёт P&L'!F12 -> 15400000 | L7: Январь | M7: =IFERROR('📋 Отчёт P&L'!B15/'📋 Отчёт P&L'!B9,0) -> 0.65 | N7: =IFERROR('📋 Отчёт P&L'!B26/'📋 Отчёт P&L'!B9,0) -> 0.20511811 | O7: =IFERROR('📋 Отчёт P&L'!B34/'📋 Отчёт P&L'!B9,0) -> 0.16431102
A8: Февраль | B8: ='📋 Отчёт P&L'!C9 -> 14000000 | C8: ='📋 Отчёт P&L'!C12+'📋 Отчёт P&L'!C24 -> 10920000 | D8: ='📋 Отчёт P&L'!C34 -> 2490500 | F8: Валовая прибыль | G8: ='📋 Отчёт P&L'!F15 -> 28600000 | I8: Оплата труда (штат) | J8: ='📋 Отчёт P&L'!F19 -> 8550000 | L8: Февраль | M8: =IFERROR('📋 Отчёт P&L'!C15/'📋 Отчёт P&L'!C9,0) -> 0.65 | N8: =IFERROR('📋 Отчёт P&L'!C26/'📋 Отчёт P&L'!C9,0) -> 0.22 | O8: =IFERROR('📋 Отчёт P&L'!C34/'📋 Отчёт P&L'!C9,0) -> 0.17789286
A9: Март | B9: ='📋 Отчёт P&L'!D9 -> 17300000 | C9: ='📋 Отчёт P&L'!D12+'📋 Отчёт P&L'!D24 -> 13215000 | D9: ='📋 Отчёт P&L'!D34 -> 3344750 | F9: Операционная прибыль | G9: ='📋 Отчёт P&L'!F26 -> 9770000 | I9: Аренда | J9: ='📋 Отчёт P&L'!F20 -> 4500000 | L9: Март | M9: =IFERROR('📋 Отчёт P&L'!D15/'📋 Отчёт P&L'!D9,0) -> 0.65 | N9: =IFERROR('📋 Отчёт P&L'!D26/'📋 Отчёт P&L'!D9,0) -> 0.23612717 | O9: =IFERROR('📋 Отчёт P&L'!D34/'📋 Отчёт P&L'!D9,0) -> 0.19333815
F10: Чистая прибыль | G10: ='📋 Отчёт P&L'!F34 -> 7922000 | I10: Маркетинг | J10: ='📋 Отчёт P&L'!F21 -> 4100000
I11: Офисные расходы | J11: ='📋 Отчёт P&L'!F22 -> 1080000
I12: Амортизация | J12: ='📋 Отчёт P&L'!F23 -> 600000
I13: Проценты по кредиту | J13: ='📋 Отчёт P&L'!F30 -> 450000
