Workbook

Sheet 📋 Воронка и CAC
A1: ЮНИТ-ЭКОНОМИКА РОЗНИЧНОГО МАГАЗИНА — Шаг 1: воронка и реальная стоимость клиента (CAC)
A2: Магазин одежды «Стиль и Ко» — расчёт за один месяц
A4: ВВОДНЫЕ ДАННЫЕ
A5: Рекламный бюджет за месяц, сум | B5: 10000000
A6: Зарплата продавцов/менеджеров (доля на привлечение), сум | B6: 4000000
A7: Получено лидов (обращений) за месяц, шт | B7: 2000
A8: Конверсия из лида в покупателя, % | B8: 0.15
A10: РАСЧЁТ "НА ПЕРВЫЙ ВЗГЛЯД" (так считают многие)
A11: Стоимость одного лида (бюджет / число лидов), сум | B11: =B5/B7 -> 5000
A12: 👉 Выглядит очень дёшево — именно эту цифру обычно показывают как "успех рекламы"
A14: РЕАЛЬНАЯ СТОИМОСТЬ КЛИЕНТА — CAC
A15: Новые покупатели за месяц (лиды × конверсия), чел | B15: =B7*B8 -> 300
A16: Все расходы на привлечение (бюджет + зарплата продаж), сум | B16: =B5+B6 -> 14000000
A17: CAC — реальная стоимость одного платящего клиента, сум | B17: =B16/B15 -> 46666.667
A18: 👉 CAC учитывает не только рекламу, но и весь путь от лида до реального покупателя —
A19: и эта цифра почти всегда оказывается в разы больше "красивой" стоимости лида

Sheet 📦 Товар – цена и маржа
A1: Шаг 2: что реально остаётся с одной единицы товара
A2: От цены на ценнике до валовой прибыли — с учётом скидок, возвратов и себестоимости
A4: ВВОДНЫЕ ДАННЫЕ
A5: Цена единицы товара (на ценнике), сум | B5: 120000
A6: Средняя скидка покупателям, % | B6: 0.15
A7: Доля возвратов от проданного, % | B7: 0.08
A8: Себестоимость единицы товара (закупка + логистика), сум | B8: 55000
A10: РАСЧЁТ ВАЛОВОЙ ПРИБЫЛИ НА ЕДИНИЦУ ТОВАРА
A11: Реальная цена после скидки, сум | B11: =B5*(1-B6) -> 102000
A12: Реальная выручка с учётом возвратов, сум | B12: =B11*(1-B7) -> 93840
A13: 👉 Скидки и возвраты "съедают" заметную часть цены ещё до расчёта прибыли
A15: ВАЛОВАЯ ПРИБЫЛЬ на единицу товара (выручка − себестоимость), сум | B15: =B12-B8 -> 38840
A16: Валовая маржа, % от реальной выручки | B16: =B15/B12 -> 0.41389599

Sheet 🧾 Чек и LTV
A1: Шаг 3: от единицы товара — к чеку и ценности клиента (LTV)
A2: Покупатель редко берёт один товар и не приходит "просто так" — считаем по чекам и повторным покупкам
A4: ВВОДНЫЕ ДАННЫЕ
A5: Глубина чека — среднее кол-во товаров в одной покупке, шт | B5: 1.8
A6: Доп. расходы на обслуживание чека (упаковка, доставка), сум | B6: 6000
A7: Частота покупок одного клиента в год, раз | B7: 2
A8: Средний срок жизни клиента, лет | B8: 1
A10: СВЯЗАННЫЕ ДАННЫЕ ИЗ ДРУГИХ ЛИСТОВ
A11: Реальная выручка с одной единицы товара, сум (лист «Товар») | B11: ='📦 Товар – цена и маржа'!B12 -> 93840
A12: Валовая прибыль с одной единицы товара, сум (лист «Товар») | B12: ='📦 Товар – цена и маржа'!B15 -> 38840
A14: СРЕДНИЙ ЧЕК И МАРЖА НА ЧЕК
A15: Средний чек, сум (глубина чека × реальная выручка с единицы) | B15: =B5*B11 -> 168912
A16: Маржа с одного чека (валовая прибыль с чека − доп.расходы), сум | B16: =B5*B12-B6 -> 63912
A18: ЦЕННОСТЬ КЛИЕНТА ЗА ВЕСЬ ПЕРИОД — LTV
A19: Количество покупок за весь срок жизни клиента (частота × срок жизни) | B19: =B7*B8 -> 2
A20: LTV — суммарная маржа от клиента за весь период, сум | B20: =B16*B19 -> 127824
A21: 👉 Если клиент не возвращается (1 покупка) — вся экономика держится на одном чеке.
A22: Каждая повторная покупка добавляет маржу почти без новых затрат на привлечение.

Sheet ⚖️ LTV vs CAC
A1: Шаг 4: главный вопрос — окупается ли клиент на самом деле?
A2: Сводим всё вместе: сколько стоил клиент и сколько он реально принесёт
A4: ИТОГОВОЕ СРАВНЕНИЕ
A5: "Красивая" стоимость лида, сум (лист «Воронка») | B5: ='📋 Воронка и CAC'!B11 -> 5000 | D5: Стоимость одного лида (бюджет / число лидов)
A6: CAC — реальная стоимость платящего клиента, сум (лист «Воронка») | B6: ='📋 Воронка и CAC'!B17 -> 46666.667
A7: LTV — ценность клиента за весь период, сум (лист «Чек и LTV») | B7: ='🧾 Чек и LTV'!B20 -> 127824
A9: КЛЮЧЕВЫЕ ПОКАЗАТЕЛИ ЗДОРОВЬЯ ЮНИТ-ЭКОНОМИКИ
A10: Соотношение LTV / CAC (ориентир здорового бизнеса — около 3x и выше) | B10: ='🧾 Чек и LTV'!B20/'📋 Воронка и CAC'!B17 -> 2.7390857 | D10: (LTV — суммарная маржа от клиента за весь период = 127 824 сум) / (CAC — реальная стоимость одного платящего клиента = 46 667 сум)
A11: Срок окупаемости клиента — сколько покупок нужно, чтобы "отбить" CAC, раз | B11: ='📋 Воронка и CAC'!B17/'🧾 Чек и LTV'!B16 -> 0.73017065 | D11: (CAC — реальная стоимость одного платящего клиента = 46 667 сум) / (Маржа с одного чека (валовая прибыль с чека − доп.расходы) = 63 912 сум)
A12: Срок окупаемости в месяцах (при заданной частоте покупок) | B12: =B11/'🧾 Чек и LTV'!B7*12 -> 4.3810239 | D12: 0,73 / Частота покупок одного клиента в год
A14: ВЫВОД
A15: Цена лида выглядит очень привлекательно — но это лишь верхушка айсберга. Когда мы считаем CAC честно (с учётом конверсии и расходов на продажи), цифра вырастает в разы. А когда сравниваем её с LTV, картина становится куда менее радужной: соотношение LTV/CAC получается заметно ниже комфортного ориентира 3x, а на то, чтобы клиент "отбил" вложенные в его привлечение деньги, нужно несколько месяцев и не одна покупка. Если клиент уйдёт раньше — бизнес попросту теряет деньги на каждом "успешно" привлечённом клиенте, хотя реклама в отчёте выглядит дешёвой и эффективной. Именно поэтому "дешёвый лид" — это НЕ юнит-экономика. Настоящая юнит-экономика — это ответ на вопрос: "Зарабатываем ли мы деньги на каждом клиенте, если посчитать вообще всё?"

Sheet 📈 Дашборд
A1: ДАШБОРД: ЮНИТ-ЭКОНОМИКА — «дешёвый лид» против реальной картины
A3: Цена лида ("красиво") | D3: CAC (реально) | G3: LTV клиента | J3: LTV / CAC
A4: ='📋 Воронка и CAC'!B11 -> 5000 | D4: ='📋 Воронка и CAC'!B17 -> 46666.667 | G4: ='🧾 Чек и LTV'!B20 -> 127824 | J4: ='⚖️ LTV vs CAC'!B10 -> 2.7390857
A8: ДАННЫЕ ДЛЯ ДИАГРАММ
A10: Воронка привлечения
A11: Этап | B11: Кол-во, чел
A12: Лиды (обращения) | B12: ='📋 Воронка и CAC'!B7 -> 2000
A13: Новые покупатели | B13: ='📋 Воронка и CAC'!B15 -> 300
A15: Из чего складывается прибыль с 1 товара
A16: Компонент | B16: Сумма, сум
A17: Себестоимость | B17: ='📦 Товар – цена и маржа'!B8 -> 55000
A18: Скидка (потеря от цены) | B18: ='📦 Товар – цена и маржа'!B5*'📦 Товар – цена и маржа'!B6 -> 18000
A19: Потери от возвратов | B19: ='📦 Товар – цена и маржа'!B11*'📦 Товар – цена и маржа'!B7 -> 8160
A20: Валовая прибыль (остаётся) | B20: ='📦 Товар – цена и маржа'!B15 -> 38840
A22: Сравнение CAC и LTV
A23: Показатель | B23: Сумма, сум
A24: CAC (стоимость клиента) | B24: ='📋 Воронка и CAC'!B17 -> 46666.667
A25: LTV (ценность клиента) | B25: ='🧾 Чек и LTV'!B20 -> 127824
A27: Чек: глубина и маржа
A28: Показатель | B28: Значение
A29: Средний чек, сум | B29: ='🧾 Чек и LTV'!B15 -> 168912
A30: Маржа с чека, сум | B30: ='🧾 Чек и LTV'!B16 -> 63912
